{"cameraMode":{"drawMode":0,"name":"Shaded","section":"Shading Mode"},"sceneLighting":true,"audioPlay":false,"sceneViewState":{"showFog":true,"showMaterialUpdate":false,"showSkybox":true,"showFlares":true,"showImageEffects":true,"showParticleSystems":true},"in2DMode":false,"pivot":{"x":-0.530409574508667,"y":1.1992065906524659,"z":-1.5490803718566895},"rotation":{"x":0.11167122423648834,"y":-0.6487752199172974,"z":0.09705764055252075,"w":0.7464585304260254},"size":7.204559326171875,"orthographic":false}